ALU.v
module parameterized_alu #(parameter WIDTH = 8)
(
input [WIDTH-1:0] A,
input [WIDTH-1:0] B,
input [2:0] opcode,
output reg [WIDTH-1:0] result,
output reg carry,
output reg zero,
output reg  overflow,
output reg negative
);

always @(*)
begin
    carry=0;
    overflow=0;

case(opcode)

3'b000: 
begin
   {carry,result} = A + B;
   overflow =(~A[WIDTH-1] & ~B[WIDTH-1] & result[WIDTH-1]) | ( A[WIDTH-1] &  B[WIDTH-1] & ~result[WIDTH-1]); 
end


3'b001:
begin
  result = A - B;
  overflow =(~A[WIDTH-1] & B[WIDTH-1] & result[WIDTH-1]) |(A[WIDTH-1] & ~B[WIDTH-1] & ~result[WIDTH-1]);
end

3'b010:
result = A & B;

3'b011:
result = A | B;

3'b100:
result = A ^ B;

3'b101:
result = A << 1;

3'b110:
result = A >> 1;

3'b111:
begin
if(A>B)
result = 1;
else
result = 0;
end

default:
result = 0;

endcase
 
if(result==0)
   zero=1;
else 
   zero=0;

if(result[WIDTH-1] == 1)
    negative = 1;
else
    negative = 0;

end

endmodule

ALU_tb.v
`timescale 1ns/100ps
module parameterized_alu_tb;

parameter WIDTH = 8;
reg [WIDTH-1:0] A;
reg [WIDTH-1:0] B;
reg [2:0] opcode;
wire [WIDTH-1:0] result;
wire carry;
wire zero;
wire overflow;
wire negative;

parameterized_alu #(WIDTH)DUT(.A(A), .B(B), .opcode(opcode), .result(result), .carry(carry), .zero(zero), .overflow(overflow), .negative(negative));

initial
begin

$dumpfile("waveform.vcd");
$dumpvars(0,parameterized_alu_tb);
$monitor("time=%d\tA=%d\tB=%d\topcode=%b\tresult=%d\tcarry=%b\tzero=%b\toverflow=%b\tnegative=%b", $time, A, B, opcode, result, carry, zero, overflow, negative);

A = 8'b10000000;
B = 8'b00000001;

opcode = 3'b000;
#10;

opcode = 3'b001;
#10;

opcode = 3'b010;
#10;

opcode = 3'b011;
#10;

opcode = 3'b100;
#10;

opcode = 3'b101;
#10;

opcode = 3'b110;
#10;

opcode = 3'b111;
#10;

$finish;

end

endmodule

waveform.vcd
$date
	Wed Jun 24 17:56:03 2026
$end
$version
	Icarus Verilog
$end
$timescale
	100ps
$end
$scope module parameterized_alu_tb $end
$var wire 1 ! zero $end
$var wire 8 " result [7:0] $end
$var wire 1 # overflow $end
$var wire 1 $ negative $end
$var wire 1 % carry $end
$var parameter 32 & WIDTH $end
$var reg 8 ' A [7:0] $end
$var reg 8 ( B [7:0] $end
$var reg 3 ) opcode [2:0] $end
$scope module DUT $end
$var wire 8 * A [7:0] $end
$var wire 8 + B [7:0] $end
$var wire 3 , opcode [2:0] $end
$var parameter 32 - WIDTH $end
$var reg 1 % carry $end
$var reg 1 $ negative $end
$var reg 1 # overflow $end
$var reg 8 . result [7:0] $end
$var reg 1 ! zero $end
$upscope $end
$upscope $end
$enddefinitions $end
$comment Show the parameter values. $end
$dumpall
b1000 -
b1000 &
$end
#0
$dumpvars
b10000001 .
b0 ,
b1 +
b10000000 *
b0 )
b1 (
b10000000 '
0%
1$
0#
b10000001 "
0!
$end
#100
0$
1#
b1111111 "
b1111111 .
b1 )
b1 ,
#200
1!
b0 "
b0 .
0#
b10 )
b10 ,
#300
1$
0!
b10000001 "
b10000001 .
b11 )
b11 ,
#400
b100 )
b100 ,
#500
0$
1!
b0 "
b0 .
b101 )
b101 ,
#600
0!
b1000000 "
b1000000 .
b110 )
b110 ,
#700
b1 "
b1 .
b111 )
b111 ,
